{"dptfxtract": {"build_requires": []}, "redhat-indexhtml": {"build_requires": []}, "mysql": {"build_requires": ["procps", "perl-Socket", "perl-Sys-Hostname", "libicu-devel", "mecab-devel", "perl-File-Temp", "perl-Getopt-Long", "perl-if", "multilib-rpm-config", "openssl", "perl-Exporter", "perl-File-Copy", "perl-IO", "libzstd-devel", "systemd", "perl-JSON", "lz4", "perl-Time", "perl-Digest-MD5", "perl-Digest", "perl-lib", "perl-libwww-perl", "perl-English", "protobuf-lite-devel", "perl-Data-Dumper", "perl-Env", "perl-POSIX", "rpcgen", "perl-File-Basename", "libevent-devel", "perl-interpreter", "time", "zlib", "bison", "perl-Time-HiRes", "libedit-devel", "openssl-devel", "make", "perl-Errno", "cmake", "lz4-devel", "gcc-c++", "libaio-devel", "perl-libs", "perl-Memoize", "perl-FindBin", "perl-Net-Ping", "zlib-devel", "perl-Fcntl", "perl-generators", "libtirpc-devel", "perl-base", "perl-Test-Simple", "perl-Carp", "perl-IPC-Open3", "rapidjson-devel", "perl-File-Find", "perl-PathTools"]}, "man-pages-overrides": {"build_requires": []}, "rubygem-tilt": {"build_requires": []}, "rust-zram-generator": {"build_requires": []}, "prefixdevname": {"build_requires": ["rust-toolset", "git", "systemd-devel"]}, "redhat-bookmarks": {"build_requires": []}, "redhat-logos": {"build_requires": ["netpbm-progs", "syslinux-perl", "hardlink"]}, "gnome-shell-extensions": {"build_requires": []}, "tigervnc": {"build_requires": ["selinux-policy-devel"]}, "java-17-openjdk": {"build_requires": ["libXi-devel", "desktop-file-utils", "gdb", "libjpeg-devel", "automake", "autoconf", "fontconfig-devel", "gcc", "libXt-devel", "libXtst-devel", "libffi-devel", "zip", "binutils", "nss-devel", "javapackages-filesystem", "xorg-x11-proto-devel", "libxslt", "libXrandr-devel", "gcc-c++", "cups-devel", "giflib-devel", "lcms2-devel", "libX11-devel", "libpng-devel", "libXinerama-devel", "elfutils-devel", "pkgconfig", "tzdata-java", "alsa-lib-devel", "systemtap-sdt-devel"]}, "hesiod": {"build_requires": ["automake", "libtool", "libidn2-devel", "autoconf"]}, "insights-client": {"build_requires": []}, "kpatch": {"build_requires": []}, "nispor": {"build_requires": []}, "mvapich2": {"build_requires": ["hwloc-devel", "rpm-mpi-hooks", "bison", "perl-Digest-MD5", "flex"]}, "mpitests": {"build_requires": []}, "qemu-kvm": {"build_requires": ["libtool", "iasl", "which", "libxkbcommon-devel", "libfdt-devel", "texinfo", "libuuid-devel", "rsync", "brlapi-devel", "cpp", "libgcrypt-devel", "numactl-devel", "ncurses-devel", "wget", "rpm-build", "libssh-devel", "check-devel", "python3-sphinx", "glusterfs-devel", "libusbx-devel", "lzo-devel", "pciutils-devel", "meson", "device-mapper-multipath-devel", "libcurl-devel", "librbd-devel", "glib2-devel", "gnutls-devel", "libattr-devel", "binutils", "ninja-build", "nss-devel", "diffutils", "usbredir-devel", "libpmem-devel", "libcacard-devel", "perl-podlators", "glusterfs-api-devel", "spice-protocol", "libaio-devel", "librados-devel", "snappy-devel", "libiscsi-devel", "perl-Test-Harness", "pixman-devel", "libpng-devel", "rdma-core-devel", "zlib-devel", "systemtap", "libepoxy-devel", "libcap-ng-devel", "python3-devel", "spice-server-devel", "systemd-devel", "libdrm-devel", "systemtap-sdt-devel", "cyrus-sasl-devel", "libseccomp-devel"]}, "kmod-kvdo": {"build_requires": []}, "pmreorder": {"build_requires": []}, "vdo": {"build_requires": []}, "stratisd": {"build_requires": []}, "compat-libgfortran-48": {"build_requires": ["zlib-devel", "binutils", "dejagnu", "elfutils-devel", "glibc", "gettext", "glibc-devel", "glibc-static", "bison", "gmp-devel", "libmpc-devel", "gdb", "mpfr-devel", "elfutils-libelf-devel", "flex", "sharutils"]}, "delve": {"build_requires": ["git", "lsof", "golang"]}, "go-toolset": {"build_requires": []}, "llvm-toolset": {"build_requires": []}, "rust-toolset": {"build_requires": []}, "lorax-templates-rhel": {"build_requires": []}, "redhat-release": {"build_requires": []}, "sap-cluster-connector": {"build_requires": []}, "resource-agents-sap": {"build_requires": []}, "compat-locales-sap": {"build_requires": []}, "libguestfs": {"build_requires": ["netpbm-progs", "ruby-devel", "ocaml-hivex-devel", "ocaml-ocamldoc", "ocaml-findlib-devel", "ocaml-gettext-devel", "perl-libintl-perl", "libvirt-daemon-kvm", "rubygem-rdoc", "squashfs-tools", "lua-devel", "gdisk", "perl-hivex", "hivex-devel", "rubygem-rake", "gfs2-utils", "libconfig-devel", "gjs", "gobject-introspection-devel", "parted", "icoutils", "po4a", "rubygem-test-unit"]}, "guestfs-tools": {"build_requires": ["libguestfs-devel", "ocaml-findlib-devel", "perl-libintl-perl", "ocaml-gettext-devel", "po4a", "libguestfs-xfs"]}, "virtio-win": {"build_requires": ["mingw32-headers", "mingw32-termcap", "mingw32-gettext-static", "mingw32-pixman", "mingw-libffi", "mingw64-winpthreads-static", "mingw32-pkg-config", "mingw64-glib2-static", "mingw64-gcc-c++", "mingw-zlib", "mingw32-crt", "mingw64-filesystem", "mingw64-gcc", "mingw-binutils-generic", "mingw32-gcc-c++", "mingw-w64-tools", "mingw64-glib2", "mingw64-crt", "mingw64-termcap", "mingw64-zlib-static", "mingw32-winpthreads-static", "mingw64-pkg-config", "mingw32-win-iconv", "mingw64-gettext-static", "mingw32-zlib-static", "mingw-filesystem-base", "mingw64-pixman", "mingw32-gcc", "mingw32-glib2", "mingw-pcre", "mingw-pkg-config", "mingw32-filesystem", "mingw64-win-iconv", "mingw32-glib2-static", "mingw64-headers"]}}