{"dptfxtract": {"build_requires": []}, "redhat-indexhtml": {"build_requires": []}, "mysql": {"build_requires": ["libzstd-devel", "perl-Fcntl", "bison", "perl-lib", "libtirpc-devel", "perl-Carp", "perl-File-Copy", "perl-File-Temp", "libaio-devel", "perl-Env", "libedit-devel", "procps", "perl-English", "make", "perl-File-Basename", "perl-FindBin", "perl-libwww-perl", "rapidjson-devel", "multilib-rpm-config", "perl-IPC-Open3", "cmake", "libevent-devel", "perl-Digest-MD5", "perl-libs", "perl-generators", "rpcgen", "openssl-devel", "time", "libicu-devel", "lz4", "perl-base", "perl-Errno", "systemd", "perl-Time-HiRes", "perl-JSON", "mecab-devel", "perl-IO", "perl-File-Find", "perl-interpreter", "zlib-devel", "lz4-devel", "perl-Digest", "perl-PathTools", "perl-Memoize", "gcc-c++", "openssl", "perl-Getopt-Long", "perl-Socket", "zlib", "perl-Exporter", "perl-Data-Dumper", "perl-Sys-Hostname", "perl-Time", "perl-Net-Ping", "perl-Test-Simple", "perl-if", "perl-POSIX", "protobuf-lite-devel"]}, "rubygem-tilt": {"build_requires": []}, "rust-zram-generator": {"build_requires": []}, "prefixdevname": {"build_requires": ["rust-toolset", "systemd-devel", "git"]}, "rhel-system-roles-sap": {"build_requires": []}, "redhat-bookmarks": {"build_requires": []}, "redhat-logos": {"build_requires": ["syslinux-perl", "netpbm-progs", "hardlink"]}, "gnome-shell-extensions": {"build_requires": []}, "tigervnc": {"build_requires": ["selinux-policy-devel"]}, "java-17-openjdk": {"build_requires": ["cups-devel", "systemtap-sdt-devel", "tzdata-java", "elfutils-devel", "autoconf", "giflib-devel", "zip", "javapackages-filesystem", "libXt-devel", "libxslt", "libjpeg-devel", "automake", "java-latest-openjdk-devel", "alsa-lib-devel", "gdb", "nss-devel", "libXtst-devel", "fontconfig-devel", "libXinerama-devel", "gcc", "binutils", "libffi-devel", "xorg-x11-proto-devel", "gcc-c++", "libpng-devel", "pkgconfig", "libXi-devel", "desktop-file-utils", "libXrandr-devel", "libX11-devel", "lcms2-devel"]}, "insights-client": {"build_requires": []}, "kpatch": {"build_requires": []}, "nispor": {"build_requires": []}, "mvapich2": {"build_requires": ["perl-Digest-MD5", "bison", "rpm-mpi-hooks", "flex", "hwloc-devel"]}, "mpitests": {"build_requires": []}, "qemu-kvm": {"build_requires": ["meson", "check-devel", "systemtap-sdt-devel", "systemd-devel", "numactl-devel", "libaio-devel", "cyrus-sasl-devel", "libpmem-devel", "gnutls-devel", "libuuid-devel", "ncurses-devel", "brlapi-devel", "rsync", "libtool", "systemtap", "libssh-devel", "libepoxy-devel", "libgcrypt-devel", "librados-devel", "librbd-devel", "libattr-devel", "usbredir-devel", "diffutils", "libiscsi-devel", "cpp", "libcacard-devel", "nss-devel", "spice-server-devel", "lzo-devel", "rpm-build", "perl-Test-Harness", "libcap-ng-devel", "snappy-devel", "python3-devel", "python3-sphinx", "texinfo", "glusterfs-devel", "libfdt-devel", "device-mapper-multipath-devel", "glib2-devel", "glusterfs-api-devel", "zlib-devel", "libxkbcommon-devel", "wget", "binutils", "pciutils-devel", "rdma-core-devel", "iasl", "libdrm-devel", "libpng-devel", "ninja-build", "libusbx-devel", "spice-protocol", "libseccomp-devel", "which", "perl-podlators", "pixman-devel", "libcurl-devel"]}, "kmod-kvdo": {"build_requires": []}, "pmreorder": {"build_requires": []}, "stratisd": {"build_requires": []}, "compat-libgfortran-48": {"build_requires": ["binutils", "bison", "mpfr-devel", "glibc-static", "libmpc-devel", "elfutils-devel", "elfutils-libelf-devel", "glibc-devel", "gmp-devel", "flex", "dejagnu", "sharutils", "zlib-devel", "gdb", "gettext", "glibc"]}, "delve": {"build_requires": ["golang", "lsof", "git"]}, "go-toolset": {"build_requires": []}, "llvm-toolset": {"build_requires": []}, "rust-toolset": {"build_requires": []}, "lorax-templates-rhel": {"build_requires": []}, "redhat-release": {"build_requires": []}, "sap-cluster-connector": {"build_requires": []}, "resource-agents-sap": {"build_requires": []}, "resource-agents-sap-hana": {"build_requires": []}, "resource-agents-sap-hana-scaleout": {"build_requires": []}, "compat-locales-sap": {"build_requires": []}, "libguestfs": {"build_requires": ["libvirt-daemon-kvm", "perl-libintl-perl", "rubygem-rake", "lua-devel", "rubygem-test-unit", "hivex-devel", "ocaml-ocamldoc", "rubygem-rdoc", "parted", "perl-hivex", "icoutils", "ocaml-hivex-devel", "libconfig-devel", "ruby-devel", "squashfs-tools", "gjs", "gfs2-utils", "gobject-introspection-devel", "ocaml-gettext-devel", "gdisk", "ocaml-findlib-devel", "perl-Sys-Virt", "po4a", "netpbm-progs"]}, "virtio-win": {"build_requires": ["mingw32-winpthreads-static", "mingw64-zlib-static", "mingw32-gcc", "mingw32-gettext-static", "mingw64-glib2-static", "mingw32-termcap", "mingw-binutils-generic", "mingw64-win-iconv", "mingw64-gcc", "mingw64-headers", "mingw32-pkg-config", "mingw64-winpthreads-static", "mingw64-pkg-config", "mingw32-win-iconv", "mingw64-filesystem", "mingw-filesystem-base", "mingw-pkg-config", "mingw32-glib2-static", "mingw-pcre", "mingw32-pixman", "mingw64-termcap", "mingw32-glib2", "mingw-zlib", "mingw32-gcc-c++", "mingw64-glib2", "mingw32-zlib-static", "mingw64-gcc-c++", "mingw-libffi", "mingw-w64-tools", "mingw64-crt", "mingw32-filesystem", "mingw64-pixman", "mingw32-headers", "mingw64-gettext-static", "mingw32-crt"]}}