{"dptfxtract": {"build_requires": []}, "redhat-indexhtml": {"build_requires": []}, "mysql": {"build_requires": ["time", "zlib", "perl-lib", "perl-libwww-perl", "perl-File-Find", "perl-Sys-Hostname", "perl-FindBin", "rpcgen", "perl-libs", "perl-JSON", "perl-IO", "perl-Time-HiRes", "perl-if", "perl-generators", "perl-File-Temp", "rapidjson-devel", "systemd", "perl-Exporter", "perl-Env", "perl-Digest-MD5", "perl-Socket", "perl-PathTools", "protobuf-lite-devel", "procps", "libevent-devel", "make", "libzstd-devel", "perl-Carp", "perl-File-Copy", "perl-IPC-Open3", "perl-Errno", "lz4", "perl-Time", "cmake", "openssl-devel", "perl-English", "libicu-devel", "perl-base", "multilib-rpm-config", "perl-Test-Simple", "zlib-devel", "libtirpc-devel", "mecab-devel", "openssl", "perl-Memoize", "bison", "gcc-c++", "perl-interpreter", "lz4-devel", "perl-Fcntl", "perl-Digest", "perl-Net-Ping", "libedit-devel", "perl-Getopt-Long", "perl-POSIX", "libaio-devel", "perl-Data-Dumper", "perl-File-Basename"]}, "rubygem-tilt": {"build_requires": []}, "rust-zram-generator": {"build_requires": []}, "prefixdevname": {"build_requires": ["rust-toolset", "git", "systemd-devel"]}, "rhel-system-roles-sap": {"build_requires": []}, "redhat-bookmarks": {"build_requires": []}, "redhat-logos": {"build_requires": ["syslinux-perl", "netpbm-progs", "hardlink"]}, "gnome-shell-extensions": {"build_requires": []}, "tigervnc": {"build_requires": ["selinux-policy-devel"]}, "java-17-openjdk": {"build_requires": ["giflib-devel", "systemtap-sdt-devel", "libffi-devel", "libX11-devel", "libXrandr-devel", "libXtst-devel", "java-latest-openjdk-devel", "libXt-devel", "zip", "libjpeg-devel", "pkgconfig", "autoconf", "javapackages-filesystem", "libXi-devel", "cups-devel", "gcc", "desktop-file-utils", "nss-devel", "fontconfig-devel", "xorg-x11-proto-devel", "libXinerama-devel", "automake", "lcms2-devel", "libxslt", "gcc-c++", "alsa-lib-devel", "binutils", "libpng-devel", "tzdata-java", "elfutils-devel", "gdb"]}, "insights-client": {"build_requires": []}, "kpatch": {"build_requires": []}, "nispor": {"build_requires": []}, "mvapich2": {"build_requires": ["flex", "bison", "hwloc-devel", "rpm-mpi-hooks", "perl-Digest-MD5"]}, "mpitests": {"build_requires": []}, "qemu-kvm": {"build_requires": ["spice-protocol", "ncurses-devel", "systemtap", "systemtap-sdt-devel", "numactl-devel", "libdrm-devel", "perl-podlators", "gnutls-devel", "perl-Test-Harness", "cyrus-sasl-devel", "libusbx-devel", "rdma-core-devel", "wget", "lzo-devel", "brlapi-devel", "libfdt-devel", "libpmem-devel", "libseccomp-devel", "pixman-devel", "libgcrypt-devel", "python3-sphinx", "iasl", "meson", "libcurl-devel", "systemd-devel", "libcacard-devel", "libssh-devel", "ninja-build", "nss-devel", "spice-server-devel", "pciutils-devel", "glusterfs-api-devel", "device-mapper-multipath-devel", "libepoxy-devel", "librados-devel", "libxkbcommon-devel", "snappy-devel", "glusterfs-devel", "which", "zlib-devel", "python3-devel", "libuuid-devel", "libiscsi-devel", "librbd-devel", "usbredir-devel", "libattr-devel", "binutils", "check-devel", "libpng-devel", "cpp", "rsync", "texinfo", "libcap-ng-devel", "libaio-devel", "libtool", "rpm-build", "glib2-devel", "diffutils"]}, "kmod-kvdo": {"build_requires": []}, "pmreorder": {"build_requires": []}, "stratisd": {"build_requires": []}, "compat-libgfortran-48": {"build_requires": ["flex", "gmp-devel", "glibc-devel", "bison", "sharutils", "mpfr-devel", "glibc-static", "libmpc-devel", "gettext", "elfutils-devel", "binutils", "elfutils-libelf-devel", "glibc", "dejagnu", "zlib-devel", "gdb"]}, "delve": {"build_requires": ["golang", "git", "lsof"]}, "go-toolset": {"build_requires": []}, "llvm-toolset": {"build_requires": []}, "rust-toolset": {"build_requires": []}, "lorax-templates-rhel": {"build_requires": []}, "redhat-release": {"build_requires": []}, "sap-cluster-connector": {"build_requires": []}, "resource-agents-sap": {"build_requires": []}, "resource-agents-sap-hana": {"build_requires": []}, "resource-agents-sap-hana-scaleout": {"build_requires": []}, "compat-locales-sap": {"build_requires": []}, "libguestfs": {"build_requires": ["rubygem-rdoc", "ocaml-findlib-devel", "gobject-introspection-devel", "hivex-devel", "po4a", "perl-hivex", "netpbm-progs", "lua-devel", "ocaml-gettext-devel", "rubygem-rake", "ocaml-ocamldoc", "icoutils", "squashfs-tools", "libconfig-devel", "perl-Sys-Virt", "gjs", "perl-libintl-perl", "ocaml-hivex-devel", "parted", "rubygem-test-unit", "gfs2-utils", "gdisk", "ruby-devel", "libvirt-daemon-kvm"]}, "virtio-win": {"build_requires": ["mingw-libffi", "mingw64-glib2-static", "mingw-binutils-generic", "mingw32-pkg-config", "mingw64-pkg-config", "mingw64-headers", "mingw64-gettext-static", "mingw32-gcc-c++", "mingw64-filesystem", "mingw64-gcc", "mingw32-glib2", "mingw32-gettext-static", "mingw-zlib", "mingw32-win-iconv", "mingw64-gcc-c++", "mingw32-gcc", "mingw32-glib2-static", "mingw-w64-tools", "mingw32-winpthreads-static", "mingw64-win-iconv", "mingw-pcre", "mingw32-headers", "mingw32-zlib-static", "mingw-filesystem-base", "mingw32-termcap", "mingw64-termcap", "mingw64-zlib-static", "mingw32-filesystem", "mingw64-crt", "mingw-pkg-config", "mingw32-pixman", "mingw32-crt", "mingw64-winpthreads-static", "mingw64-pixman", "mingw64-glib2"]}}