{"dptfxtract": {"build_requires": []}, "redhat-indexhtml": {"build_requires": []}, "mysql": {"build_requires": ["lz4", "libevent-devel", "perl-libs", "gcc-c++", "time", "perl-POSIX", "perl-File-Find", "perl-Memoize", "libedit-devel", "perl-Sys-Hostname", "lz4-devel", "protobuf-lite-devel", "perl-Carp", "perl-Errno", "libaio-devel", "perl-generators", "zlib", "perl-Exporter", "zlib-devel", "perl-JSON", "perl-Net-Ping", "procps", "perl-Test-Simple", "perl-base", "libzstd-devel", "perl-Env", "perl-File-Copy", "perl-Digest", "libtirpc-devel", "perl-File-Temp", "bison", "perl-FindBin", "perl-if", "perl-Time", "openssl-devel", "openssl", "libicu-devel", "perl-libwww-perl", "perl-PathTools", "perl-Socket", "cmake", "make", "perl-Digest-MD5", "perl-Time-HiRes", "perl-Getopt-Long", "rpcgen", "perl-Fcntl", "systemd", "perl-interpreter", "perl-IPC-Open3", "mecab-devel", "rapidjson-devel", "perl-English", "perl-lib", "multilib-rpm-config", "perl-IO", "perl-File-Basename", "perl-Data-Dumper"]}, "rubygem-tilt": {"build_requires": []}, "rust-zram-generator": {"build_requires": []}, "prefixdevname": {"build_requires": ["systemd-devel", "git", "rust-toolset"]}, "redhat-bookmarks": {"build_requires": []}, "redhat-logos": {"build_requires": ["netpbm-progs", "hardlink", "syslinux-perl"]}, "gnome-shell-extensions": {"build_requires": []}, "tigervnc": {"build_requires": ["selinux-policy-devel"]}, "dotnet6.0": {"build_requires": []}, "java-17-openjdk": {"build_requires": ["libxslt", "elfutils-devel", "libXtst-devel", "gcc-c++", "fontconfig-devel", "javapackages-filesystem", "binutils", "lcms2-devel", "zip", "xorg-x11-proto-devel", "java-latest-openjdk-devel", "giflib-devel", "tzdata-java", "desktop-file-utils", "nss-devel", "libXrandr-devel", "libpng-devel", "gcc", "systemtap-sdt-devel", "libXinerama-devel", "autoconf", "libjpeg-devel", "libX11-devel", "libffi-devel", "libXi-devel", "alsa-lib-devel", "libXt-devel", "gdb", "automake", "cups-devel", "pkgconfig"]}, "insights-client": {"build_requires": []}, "kpatch": {"build_requires": []}, "nispor": {"build_requires": []}, "mvapich2": {"build_requires": ["bison", "hwloc-devel", "rpm-mpi-hooks", "perl-Digest-MD5", "flex"]}, "mpitests": {"build_requires": []}, "qemu-kvm": {"build_requires": ["lzo-devel", "libgcrypt-devel", "librados-devel", "brlapi-devel", "meson", "libtool", "glusterfs-devel", "which", "spice-server-devel", "systemd-devel", "perl-Test-Harness", "libusbx-devel", "libattr-devel", "binutils", "systemtap", "libaio-devel", "libepoxy-devel", "iasl", "libfdt-devel", "zlib-devel", "libiscsi-devel", "texinfo", "wget", "libssh-devel", "libcacard-devel", "ninja-build", "nss-devel", "gnutls-devel", "cyrus-sasl-devel", "libpng-devel", "glib2-devel", "pciutils-devel", "rsync", "rpm-build", "systemtap-sdt-devel", "ncurses-devel", "cpp", "numactl-devel", "perl-podlators", "spice-protocol", "libcurl-devel", "libcap-ng-devel", "usbredir-devel", "libxkbcommon-devel", "pixman-devel", "diffutils", "snappy-devel", "python3-devel", "python3-sphinx", "glusterfs-api-devel", "libpmem-devel", "libseccomp-devel", "rdma-core-devel", "libdrm-devel", "check-devel", "libuuid-devel", "librbd-devel", "device-mapper-multipath-devel"]}, "kmod-kvdo": {"build_requires": []}, "pmreorder": {"build_requires": []}, "stratisd": {"build_requires": []}, "compat-libgfortran-48": {"build_requires": ["mpfr-devel", "bison", "gmp-devel", "elfutils-devel", "zlib-devel", "sharutils", "dejagnu", "libmpc-devel", "glibc-static", "gettext", "flex", "glibc", "elfutils-libelf-devel", "gdb", "binutils", "glibc-devel"]}, "delve": {"build_requires": ["golang", "lsof", "git"]}, "go-toolset": {"build_requires": []}, "llvm-toolset": {"build_requires": []}, "rust-toolset": {"build_requires": []}, "lorax-templates-rhel": {"build_requires": []}, "redhat-release": {"build_requires": []}, "libguestfs": {"build_requires": ["icoutils", "libconfig-devel", "hivex-devel", "perl-libintl-perl", "squashfs-tools", "parted", "ocaml-hivex-devel", "po4a", "rubygem-rdoc", "ocaml-findlib-devel", "gfs2-utils", "gjs", "perl-hivex", "libvirt-daemon-kvm", "lua-devel", "gobject-introspection-devel", "rubygem-rake", "netpbm-progs", "gdisk", "rubygem-test-unit", "ocaml-gettext-devel", "ruby-devel", "ocaml-ocamldoc", "perl-Sys-Virt"]}, "virtio-win": {"build_requires": ["mingw32-glib2", "mingw32-pkg-config", "mingw64-winpthreads-static", "mingw64-termcap", "mingw-pcre", "mingw64-gettext-static", "mingw32-crt", "mingw32-win-iconv", "mingw64-headers", "mingw32-termcap", "mingw32-headers", "mingw64-crt", "mingw32-pixman", "mingw32-filesystem", "mingw32-glib2-static", "mingw64-pixman", "mingw-filesystem-base", "mingw32-gcc-c++", "mingw64-filesystem", "mingw32-gettext-static", "mingw64-gcc", "mingw64-glib2-static", "mingw-libffi", "mingw-pkg-config", "mingw64-gcc-c++", "mingw-w64-tools", "mingw-zlib", "mingw64-zlib-static", "mingw32-winpthreads-static", "mingw32-gcc", "mingw-binutils-generic", "mingw32-zlib-static", "mingw64-pkg-config", "mingw64-glib2", "mingw64-win-iconv"]}}