{"dptfxtract": {"build_requires": []}, "redhat-indexhtml": {"build_requires": []}, "mysql": {"build_requires": ["perl-Data-Dumper", "perl-base", "perl-Memoize", "perl-PathTools", "zlib-devel", "protobuf-lite-devel", "perl-if", "perl-libwww-perl", "bison", "perl-POSIX", "perl-Net-Ping", "perl-Test-Simple", "time", "zlib", "perl-IPC-Open3", "perl-Time-HiRes", "perl-Sys-Hostname", "perl-lib", "perl-interpreter", "perl-Getopt-Long", "perl-generators", "rpcgen", "perl-Socket", "make", "perl-Env", "perl-Exporter", "multilib-rpm-config", "openssl-devel", "libzstd-devel", "libicu-devel", "libevent-devel", "procps", "libedit-devel", "perl-File-Basename", "perl-JSON", "libtirpc-devel", "gcc-c++", "perl-English", "perl-Digest", "perl-libs", "perl-FindBin", "lz4-devel", "perl-File-Find", "rapidjson-devel", "systemd", "perl-Errno", "libaio-devel", "perl-Carp", "cmake", "mecab-devel", "openssl", "perl-Digest-MD5", "perl-Fcntl", "perl-File-Copy", "perl-Time", "lz4", "perl-File-Temp", "perl-IO"]}, "man-pages-overrides": {"build_requires": []}, "rubygem-tilt": {"build_requires": []}, "rust-zram-generator": {"build_requires": []}, "prefixdevname": {"build_requires": ["systemd-devel", "rust-toolset", "git"]}, "rhel-system-roles-sap": {"build_requires": []}, "redhat-bookmarks": {"build_requires": []}, "redhat-logos": {"build_requires": ["hardlink", "netpbm-progs", "syslinux-perl"]}, "gnome-shell-extensions": {"build_requires": []}, "tigervnc": {"build_requires": ["selinux-policy-devel"]}, "dotnet6.0": {"build_requires": []}, "java-17-openjdk": {"build_requires": ["alsa-lib-devel", "javapackages-filesystem", "elfutils-devel", "libXi-devel", "tzdata-java", "libpng-devel", "libXinerama-devel", "libjpeg-devel", "autoconf", "lcms2-devel", "gcc", "libX11-devel", "fontconfig-devel", "libffi-devel", "libXt-devel", "libxslt", "desktop-file-utils", "systemtap-sdt-devel", "pkgconfig", "automake", "xorg-x11-proto-devel", "gcc-c++", "binutils", "cups-devel", "libXrandr-devel", "nss-devel", "giflib-devel", "gdb", "zip", "libXtst-devel"]}, "hesiod": {"build_requires": ["libidn2-devel", "automake", "libtool", "autoconf"]}, "insights-client": {"build_requires": []}, "kpatch": {"build_requires": []}, "realtime-tests": {"build_requires": ["numactl-devel", "make", "python3-devel", "gcc"]}, "rteval": {"build_requires": ["python3-devel"]}, "rteval-loads": {"build_requires": ["glibc-devel", "zlib-devel", "gcc", "kernel-headers", "libaio-devel", "libcap-devel", "keyutils-libs-devel", "lksctp-tools-devel", "libattr-devel"]}, "realtime-setup": {"build_requires": ["systemd", "annobin", "gcc"]}, "nispor": {"build_requires": []}, "mvapich2": {"build_requires": ["hwloc-devel", "bison", "perl-Digest-MD5", "rpm-mpi-hooks", "flex"]}, "mpitests": {"build_requires": []}, "kmod-kvdo": {"build_requires": []}, "pmreorder": {"build_requires": []}, "vdo": {"build_requires": []}, "stratisd": {"build_requires": []}, "compat-libgfortran-48": {"build_requires": ["libmpc-devel", "mpfr-devel", "elfutils-libelf-devel", "gettext", "zlib-devel", "glibc-devel", "sharutils", "elfutils-devel", "glibc-static", "bison", "gdb", "dejagnu", "binutils", "glibc", "gmp-devel", "flex"]}, "delve": {"build_requires": ["golang", "lsof", "git"]}, "go-toolset": {"build_requires": []}, "llvm-toolset": {"build_requires": []}, "rust-toolset": {"build_requires": []}, "lorax-templates-rhel": {"build_requires": []}, "redhat-release": {"build_requires": []}, "sap-cluster-connector": {"build_requires": []}, "resource-agents-sap": {"build_requires": []}, "resource-agents-sap-hana": {"build_requires": []}, "resource-agents-sap-hana-scaleout": {"build_requires": []}, "compat-locales-sap": {"build_requires": []}, "qemu-kvm": {"build_requires": ["zlib-devel", "device-mapper-multipath-devel", "librados-devel", "diffutils", "libdrm-devel", "libpmem-devel", "libseccomp-devel", "libtool", "libattr-devel", "libpng-devel", "libusbx-devel", "iasl", "ncurses-devel", "libfdt-devel", "pciutils-devel", "pixman-devel", "wget", "lzo-devel", "libgcrypt-devel", "usbredir-devel", "rdma-core-devel", "libuuid-devel", "libcacard-devel", "rsync", "which", "glusterfs-devel", "libiscsi-devel", "python3-devel", "systemtap-sdt-devel", "texinfo", "snappy-devel", "perl-podlators", "libxkbcommon-devel", "libcap-ng-devel", "librbd-devel", "cpp", "systemd-devel", "rpm-build", "ninja-build", "systemtap", "brlapi-devel", "binutils", "meson", "libcurl-devel", "gnutls-devel", "glusterfs-api-devel", "nss-devel", "spice-server-devel", "libaio-devel", "check-devel", "glib2-devel", "python3-sphinx", "libepoxy-devel", "libssh-devel", "numactl-devel", "perl-Test-Harness", "cyrus-sasl-devel", "spice-protocol"]}, "libguestfs": {"build_requires": ["rubygem-rdoc", "gobject-introspection-devel", "rubygem-rake", "gfs2-utils", "perl-libintl-perl", "ruby-devel", "icoutils", "ocaml-gettext-devel", "netpbm-progs", "parted", "hivex-devel", "libconfig-devel", "gdisk", "ocaml-hivex-devel", "perl-hivex", "rubygem-test-unit", "ocaml-findlib-devel", "lua-devel", "squashfs-tools", "po4a", "ocaml-ocamldoc", "gjs", "libvirt-daemon-kvm"]}, "guestfs-tools": {"build_requires": ["ocaml-findlib-devel", "ocaml-gettext-devel", "po4a", "libguestfs-devel", "libguestfs-xfs", "perl-libintl-perl"]}, "virt-v2v": {"build_requires": ["ocaml-findlib-devel", "mingw-filesystem", "ocaml-gettext-devel", "ocaml-fileutils-devel", "mingw-headers", "mingw-crt", "po4a", "libguestfs", "mingw-gcc", "mingw-binutils"]}, "libguestfs-winsupport": {"build_requires": ["libconfig-devel"]}, "virtio-win": {"build_requires": ["mingw32-glib2-static", "mingw32-gcc", "mingw32-pixman", "mingw64-gcc-c++", "mingw-zlib", "mingw64-zlib-static", "mingw32-termcap", "mingw32-headers", "mingw32-win-iconv", "mingw64-gettext-static", "mingw32-zlib-static", "mingw-w64-tools", "mingw64-termcap", "mingw64-pkg-config", "mingw-pkg-config", "mingw64-winpthreads-static", "mingw64-pixman", "mingw-filesystem-base", "mingw32-filesystem", "mingw-pcre", "mingw64-gcc", "mingw32-crt", "mingw32-winpthreads-static", "mingw-binutils-generic", "mingw32-pkg-config", "mingw64-glib2", "mingw32-gettext-static", "mingw32-gcc-c++", "mingw-libffi", "mingw64-win-iconv", "mingw32-glib2", "mingw64-glib2-static", "mingw64-crt", "mingw64-headers", "mingw64-filesystem"]}}