{"dptfxtract": {"build_requires": []}, "redhat-indexhtml": {"build_requires": []}, "mysql": {"build_requires": ["perl-libwww-perl", "perl-Data-Dumper", "perl-Time", "perl-Fcntl", "zlib", "zlib-devel", "cmake", "gcc-c++", "libicu-devel", "multilib-rpm-config", "perl-Socket", "lz4-devel", "perl-Env", "perl-Sys-Hostname", "perl-Exporter", "perl-Getopt-Long", "perl-PathTools", "perl-interpreter", "time", "libaio-devel", "perl-Digest-MD5", "perl-lib", "perl-Digest", "bison", "perl-POSIX", "perl-English", "libevent-devel", "libzstd-devel", "libedit-devel", "make", "perl-base", "perl-libs", "openssl", "rapidjson-devel", "perl-File-Basename", "perl-if", "perl-IO", "perl-Test-Simple", "perl-File-Copy", "perl-File-Temp", "procps", "perl-File-Find", "perl-Time-HiRes", "rpcgen", "lz4", "perl-IPC-Open3", "perl-FindBin", "perl-generators", "openssl-devel", "perl-Net-Ping", "libtirpc-devel", "systemd", "perl-Errno", "mecab-devel", "perl-Carp", "perl-Memoize", "perl-JSON", "protobuf-lite-devel"]}, "rubygem-tilt": {"build_requires": []}, "rust-zram-generator": {"build_requires": []}, "prefixdevname": {"build_requires": ["systemd-devel", "git", "rust-toolset"]}, "redhat-bookmarks": {"build_requires": []}, "redhat-logos": {"build_requires": ["netpbm-progs", "syslinux-perl", "hardlink"]}, "gnome-shell-extensions": {"build_requires": []}, "tigervnc": {"build_requires": ["selinux-policy-devel"]}, "dotnet6.0": {"build_requires": []}, "java-17-openjdk": {"build_requires": ["fontconfig-devel", "zip", "cups-devel", "libXinerama-devel", "binutils", "automake", "xorg-x11-proto-devel", "gcc-c++", "java-latest-openjdk-devel", "libffi-devel", "libXtst-devel", "desktop-file-utils", "libxslt", "systemtap-sdt-devel", "elfutils-devel", "libX11-devel", "libXrandr-devel", "alsa-lib-devel", "libXt-devel", "autoconf", "javapackages-filesystem", "libXi-devel", "gdb", "gcc", "libjpeg-devel", "libpng-devel", "giflib-devel", "lcms2-devel", "tzdata-java", "nss-devel", "pkgconfig"]}, "insights-client": {"build_requires": []}, "kpatch": {"build_requires": []}, "nispor": {"build_requires": []}, "mvapich2": {"build_requires": ["hwloc-devel", "flex", "rpm-mpi-hooks", "perl-Digest-MD5", "bison"]}, "mpitests": {"build_requires": []}, "qemu-kvm": {"build_requires": ["libdrm-devel", "librbd-devel", "usbredir-devel", "libepoxy-devel", "spice-protocol", "libcurl-devel", "binutils", "rdma-core-devel", "gnutls-devel", "zlib-devel", "rsync", "python3-sphinx", "systemd-devel", "glib2-devel", "libgcrypt-devel", "rpm-build", "libxkbcommon-devel", "systemtap-sdt-devel", "device-mapper-multipath-devel", "diffutils", "libcacard-devel", "pciutils-devel", "perl-podlators", "libaio-devel", "check-devel", "cpp", "libssh-devel", "perl-Test-Harness", "iasl", "libseccomp-devel", "numactl-devel", "libuuid-devel", "which", "lzo-devel", "ncurses-devel", "ninja-build", "spice-server-devel", "brlapi-devel", "glusterfs-devel", "snappy-devel", "systemtap", "pixman-devel", "libattr-devel", "libiscsi-devel", "glusterfs-api-devel", "python3-devel", "libtool", "texinfo", "meson", "libusbx-devel", "libfdt-devel", "libpng-devel", "libcap-ng-devel", "libpmem-devel", "nss-devel", "librados-devel", "wget", "cyrus-sasl-devel"]}, "kmod-kvdo": {"build_requires": []}, "pmreorder": {"build_requires": []}, "stratisd": {"build_requires": []}, "compat-libgfortran-48": {"build_requires": ["mpfr-devel", "flex", "glibc-static", "glibc", "sharutils", "glibc-devel", "libmpc-devel", "dejagnu", "gdb", "binutils", "gmp-devel", "elfutils-libelf-devel", "zlib-devel", "gettext", "elfutils-devel", "bison"]}, "delve": {"build_requires": ["golang", "lsof", "git"]}, "go-toolset": {"build_requires": []}, "llvm-toolset": {"build_requires": []}, "rust-toolset": {"build_requires": []}, "lorax-templates-rhel": {"build_requires": []}, "redhat-release": {"build_requires": []}, "libguestfs": {"build_requires": ["po4a", "parted", "gobject-introspection-devel", "ocaml-hivex-devel", "hivex-devel", "libconfig-devel", "perl-libintl-perl", "ocaml-gettext-devel", "ocaml-ocamldoc", "squashfs-tools", "perl-hivex", "ocaml-findlib-devel", "rubygem-test-unit", "lua-devel", "gjs", "icoutils", "netpbm-progs", "libvirt-daemon-kvm", "rubygem-rake", "gfs2-utils", "rubygem-rdoc", "ruby-devel", "perl-Sys-Virt", "gdisk"]}, "virtio-win": {"build_requires": ["mingw-binutils-generic", "mingw64-headers", "mingw32-win-iconv", "mingw64-glib2-static", "mingw-pkg-config", "mingw-libffi", "mingw64-pkg-config", "mingw32-gettext-static", "mingw64-gcc-c++", "mingw64-zlib-static", "mingw64-gcc", "mingw32-glib2-static", "mingw32-glib2", "mingw64-crt", "mingw-zlib", "mingw64-pixman", "mingw64-filesystem", "mingw-w64-tools", "mingw64-glib2", "mingw32-crt", "mingw32-headers", "mingw64-gettext-static", "mingw32-pkg-config", "mingw32-winpthreads-static", "mingw64-win-iconv", "mingw32-gcc-c++", "mingw-pcre", "mingw32-gcc", "mingw-filesystem-base", "mingw64-winpthreads-static", "mingw32-pixman", "mingw64-termcap", "mingw32-filesystem", "mingw32-zlib-static", "mingw32-termcap"]}}