{"dptfxtract": {"build_requires": []}, "redhat-indexhtml": {"build_requires": []}, "mysql": {"build_requires": ["libtirpc-devel", "perl-Carp", "perl-Exporter", "perl-Test-Simple", "zlib", "perl-Errno", "perl-IPC-Open3", "perl-File-Copy", "protobuf-lite-devel", "mecab-devel", "perl-File-Find", "perl-Net-Ping", "rapidjson-devel", "libedit-devel", "bison", "gcc-c++", "lz4", "perl-Getopt-Long", "perl-Env", "openssl-devel", "multilib-rpm-config", "perl-generators", "perl-libwww-perl", "perl-Memoize", "perl-PathTools", "perl-Sys-Hostname", "systemd", "perl-Data-Dumper", "cmake", "perl-Digest", "perl-English", "libaio-devel", "perl-base", "perl-FindBin", "perl-POSIX", "lz4-devel", "time", "perl-Time", "procps", "rpcgen", "perl-Socket", "perl-interpreter", "perl-lib", "make", "perl-File-Temp", "zlib-devel", "perl-if", "perl-Digest-MD5", "libicu-devel", "openssl", "libevent-devel", "perl-IO", "libzstd-devel", "perl-Time-HiRes", "perl-File-Basename", "perl-libs", "perl-JSON", "perl-Fcntl"]}, "man-pages-overrides": {"build_requires": []}, "rubygem-tilt": {"build_requires": []}, "rust-zram-generator": {"build_requires": []}, "prefixdevname": {"build_requires": ["systemd-devel", "rust-toolset", "git"]}, "redhat-bookmarks": {"build_requires": []}, "redhat-logos": {"build_requires": ["netpbm-progs", "hardlink", "syslinux-perl"]}, "gnome-shell-extensions": {"build_requires": []}, "tigervnc": {"build_requires": ["selinux-policy-devel"]}, "dotnet6.0": {"build_requires": []}, "java-17-openjdk": {"build_requires": ["binutils", "cups-devel", "systemtap-sdt-devel", "libXrandr-devel", "libX11-devel", "libxslt", "fontconfig-devel", "nss-devel", "tzdata-java", "gcc-c++", "libXtst-devel", "automake", "autoconf", "giflib-devel", "libpng-devel", "pkgconfig", "javapackages-filesystem", "libXt-devel", "zip", "desktop-file-utils", "xorg-x11-proto-devel", "lcms2-devel", "libjpeg-devel", "libXinerama-devel", "alsa-lib-devel", "libXi-devel", "gdb", "gcc", "libffi-devel", "elfutils-devel"]}, "hesiod": {"build_requires": ["libidn-devel", "autoconf", "libtool", "automake"]}, "insights-client": {"build_requires": []}, "kpatch": {"build_requires": []}, "nispor": {"build_requires": []}, "mvapich2": {"build_requires": ["perl-Digest-MD5", "bison", "flex", "hwloc-devel", "rpm-mpi-hooks"]}, "mpitests": {"build_requires": []}, "qemu-kvm": {"build_requires": ["texinfo", "binutils", "libattr-devel", "device-mapper-multipath-devel", "diffutils", "iasl", "systemtap-sdt-devel", "cyrus-sasl-devel", "libtool", "brlapi-devel", "glib2-devel", "usbredir-devel", "wget", "systemtap", "nss-devel", "pciutils-devel", "spice-server-devel", "rdma-core-devel", "pixman-devel", "cpp", "libgcrypt-devel", "lzo-devel", "meson", "python3-sphinx", "libfdt-devel", "libaio-devel", "libxkbcommon-devel", "libdrm-devel", "libpng-devel", "rpm-build", "numactl-devel", "ninja-build", "perl-podlators", "libiscsi-devel", "ncurses-devel", "libpmem-devel", "systemd-devel", "zlib-devel", "spice-protocol", "check-devel", "librados-devel", "libcurl-devel", "glusterfs-api-devel", "libepoxy-devel", "librbd-devel", "rsync", "libcap-ng-devel", "libssh-devel", "gnutls-devel", "snappy-devel", "libuuid-devel", "glusterfs-devel", "libseccomp-devel", "libusbx-devel", "perl-Test-Harness", "which", "python3-devel", "libcacard-devel"]}, "kmod-kvdo": {"build_requires": []}, "pmreorder": {"build_requires": []}, "stratisd": {"build_requires": []}, "compat-libgfortran-48": {"build_requires": ["glibc-devel", "glibc-static", "mpfr-devel", "binutils", "bison", "gettext", "libmpc-devel", "glibc", "sharutils", "gmp-devel", "gdb", "zlib-devel", "dejagnu", "flex", "elfutils-libelf-devel", "elfutils-devel"]}, "delve": {"build_requires": ["golang", "lsof", "git"]}, "go-toolset": {"build_requires": []}, "llvm-toolset": {"build_requires": []}, "rust-toolset": {"build_requires": []}, "lorax-templates-rhel": {"build_requires": []}, "redhat-release": {"build_requires": []}, "libguestfs": {"build_requires": ["rubygem-rake", "rubygem-test-unit", "icoutils", "ocaml-findlib-devel", "squashfs-tools", "po4a", "gobject-introspection-devel", "hivex-devel", "libconfig-devel", "lua-devel", "libvirt-daemon-kvm", "parted", "gfs2-utils", "perl-libintl-perl", "perl-Sys-Virt", "gdisk", "ocaml-gettext-devel", "ocaml-hivex-devel", "ruby-devel", "ocaml-ocamldoc", "rubygem-rdoc", "gjs", "perl-hivex", "netpbm-progs"]}, "virtio-win": {"build_requires": ["mingw32-zlib-static", "mingw32-winpthreads-static", "mingw64-pkg-config", "mingw32-headers", "mingw-binutils-generic", "mingw-pkg-config", "mingw64-gcc-c++", "mingw64-zlib-static", "mingw64-glib2", "mingw-filesystem-base", "mingw64-gcc", "mingw32-crt", "mingw32-filesystem", "mingw64-win-iconv", "mingw64-filesystem", "mingw-libffi", "mingw32-glib2-static", "mingw32-glib2", "mingw32-pkg-config", "mingw64-termcap", "mingw32-gettext-static", "mingw32-win-iconv", "mingw64-crt", "mingw64-glib2-static", "mingw64-winpthreads-static", "mingw32-termcap", "mingw-pcre", "mingw-zlib", "mingw32-pixman", "mingw64-pixman", "mingw-w64-tools", "mingw32-gcc", "mingw64-gettext-static", "mingw32-gcc-c++", "mingw64-headers"]}}