{"dptfxtract": {"build_requires": []}, "redhat-indexhtml": {"build_requires": []}, "mysql": {"build_requires": ["perl-libwww-perl", "perl-generators", "bison", "perl-Exporter", "libaio-devel", "openssl", "zlib", "lz4-devel", "perl-if", "perl-Socket", "perl-Time-HiRes", "openssl-devel", "time", "perl-Memoize", "perl-Errno", "perl-IPC-Open3", "lz4", "cmake", "perl-Digest-MD5", "perl-Getopt-Long", "perl-FindBin", "libedit-devel", "rpcgen", "protobuf-lite-devel", "libzstd-devel", "perl-IO", "perl-File-Temp", "rapidjson-devel", "perl-lib", "libicu-devel", "systemd", "libevent-devel", "perl-POSIX", "perl-Carp", "perl-Data-Dumper", "gcc-c++", "perl-File-Find", "perl-libs", "perl-interpreter", "perl-PathTools", "perl-Time", "perl-Net-Ping", "perl-File-Copy", "mecab-devel", "perl-Env", "procps", "perl-Fcntl", "perl-File-Basename", "perl-Test-Simple", "perl-Digest", "perl-JSON", "multilib-rpm-config", "perl-base", "libtirpc-devel", "perl-Sys-Hostname", "zlib-devel", "perl-English", "make"]}, "rubygem-tilt": {"build_requires": []}, "rust-zram-generator": {"build_requires": []}, "prefixdevname": {"build_requires": ["git", "rust-toolset", "systemd-devel"]}, "rhel-system-roles-sap": {"build_requires": []}, "redhat-bookmarks": {"build_requires": []}, "redhat-logos": {"build_requires": ["netpbm-progs", "hardlink", "syslinux-perl"]}, "gnome-shell-extensions": {"build_requires": []}, "tigervnc": {"build_requires": ["selinux-policy-devel"]}, "dotnet6.0": {"build_requires": []}, "java-17-openjdk": {"build_requires": ["binutils", "cups-devel", "libjpeg-devel", "pkgconfig", "alsa-lib-devel", "systemtap-sdt-devel", "desktop-file-utils", "javapackages-filesystem", "nss-devel", "libXi-devel", "libffi-devel", "java-latest-openjdk-devel", "libXtst-devel", "libXrandr-devel", "fontconfig-devel", "elfutils-devel", "lcms2-devel", "libXinerama-devel", "gcc-c++", "libxslt", "gdb", "libX11-devel", "giflib-devel", "zip", "libpng-devel", "tzdata-java", "libXt-devel", "gcc", "automake", "autoconf", "xorg-x11-proto-devel"]}, "insights-client": {"build_requires": []}, "kpatch": {"build_requires": []}, "kernel-rt": {"build_requires": ["binutils", "perl-generators", "coreutils", "hmaccalc", "net-tools", "bison", "openssl", "openssl-devel", "python3-devel", "findutils", "rpm-build", "bash", "m4", "elfutils-devel", "gawk", "perl-Carp", "perl-interpreter", "flex", "elfutils", "bzip2", "gzip", "diffutils", "xz", "which", "bc", "patch", "kmod", "git", "tar", "redhat-rpm-config", "hostname", "gcc", "dwarves", "perl-devel", "make"]}, "tuned": {"build_requires": []}, "realtime-tests": {"build_requires": ["numactl-devel", "python3-devel", "make", "gcc"]}, "rteval": {"build_requires": ["python3-devel"]}, "rteval-loads": {"build_requires": ["libaio-devel", "glibc-devel", "gcc", "libattr-devel", "libcap-devel", "keyutils-libs-devel", "zlib-devel", "kernel-headers", "lksctp-tools-devel"]}, "realtime-setup": {"build_requires": ["annobin", "systemd", "gcc"]}, "nispor": {"build_requires": []}, "mvapich2": {"build_requires": ["flex", "bison", "hwloc-devel", "rpm-mpi-hooks", "perl-Digest-MD5"]}, "mpitests": {"build_requires": []}, "qemu-kvm": {"build_requires": ["binutils", "cpp", "snappy-devel", "gnutls-devel", "check-devel", "libaio-devel", "libcurl-devel", "ncurses-devel", "systemtap", "iasl", "systemtap-sdt-devel", "ninja-build", "libxkbcommon-devel", "usbredir-devel", "texinfo", "python3-devel", "nss-devel", "spice-protocol", "lzo-devel", "rpm-build", "libtool", "rdma-core-devel", "pciutils-devel", "libepoxy-devel", "numactl-devel", "spice-server-devel", "libattr-devel", "libssh-devel", "perl-Test-Harness", "cyrus-sasl-devel", "libcap-ng-devel", "libdrm-devel", "python3-sphinx", "libseccomp-devel", "brlapi-devel", "systemd-devel", "glib2-devel", "libcacard-devel", "libiscsi-devel", "libgcrypt-devel", "rsync", "diffutils", "librados-devel", "glusterfs-devel", "wget", "glusterfs-api-devel", "libfdt-devel", "device-mapper-multipath-devel", "libusbx-devel", "libpng-devel", "which", "librbd-devel", "libuuid-devel", "perl-podlators", "libpmem-devel", "pixman-devel", "zlib-devel", "meson"]}, "kmod-kvdo": {"build_requires": []}, "pmreorder": {"build_requires": []}, "stratisd": {"build_requires": []}, "compat-libgfortran-48": {"build_requires": ["binutils", "mpfr-devel", "dejagnu", "flex", "glibc-static", "gettext", "bison", "libmpc-devel", "sharutils", "gdb", "gmp-devel", "glibc", "elfutils-devel", "glibc-devel", "zlib-devel", "elfutils-libelf-devel"]}, "delve": {"build_requires": ["golang", "git", "lsof"]}, "go-toolset": {"build_requires": []}, "llvm-toolset": {"build_requires": []}, "rust-toolset": {"build_requires": []}, "lorax-templates-rhel": {"build_requires": []}, "redhat-release": {"build_requires": []}, "sap-cluster-connector": {"build_requires": []}, "resource-agents-sap": {"build_requires": []}, "resource-agents-sap-hana": {"build_requires": []}, "resource-agents-sap-hana-scaleout": {"build_requires": []}, "compat-locales-sap": {"build_requires": []}, "libguestfs": {"build_requires": ["perl-hivex", "perl-Sys-Virt", "netpbm-progs", "gobject-introspection-devel", "ocaml-hivex-devel", "libconfig-devel", "lua-devel", "po4a", "ocaml-ocamldoc", "ruby-devel", "gjs", "libvirt-daemon-kvm", "parted", "ocaml-findlib-devel", "rubygem-rdoc", "gdisk", "rubygem-test-unit", "squashfs-tools", "rubygem-rake", "ocaml-gettext-devel", "hivex-devel", "icoutils", "perl-libintl-perl", "gfs2-utils"]}, "virt-v2v": {"build_requires": ["mingw-gcc", "mingw-filesystem", "ocaml-findlib-devel", "ocaml-gettext-devel", "mingw-crt", "libguestfs", "mingw-headers", "mingw-binutils", "ocaml-fileutils-devel", "po4a"]}, "libguestfs-winsupport": {"build_requires": ["libconfig-devel"]}, "virtio-win": {"build_requires": ["mingw32-headers", "mingw32-gcc-c++", "mingw64-pixman", "mingw-zlib", "mingw64-gcc-c++", "mingw-w64-tools", "mingw64-zlib-static", "mingw64-glib2-static", "mingw64-pkg-config", "mingw64-crt", "mingw-binutils-generic", "mingw-filesystem-base", "mingw64-filesystem", "mingw-libffi", "mingw64-winpthreads-static", "mingw64-gettext-static", "mingw32-gcc", "mingw32-glib2", "mingw32-crt", "mingw-pcre", "mingw32-termcap", "mingw32-zlib-static", "mingw32-pixman", "mingw64-termcap", "mingw32-glib2-static", "mingw32-win-iconv", "mingw32-pkg-config", "mingw32-filesystem", "mingw64-win-iconv", "mingw32-gettext-static", "mingw32-winpthreads-static", "mingw-pkg-config", "mingw64-glib2", "mingw64-headers", "mingw64-gcc"]}}